ml-wg/__init__.py
ml-wg/classification/__init__.py
ml-wg/classification/graph_kernels.py
ml-wg/classification/wl_kernel.py
ml-wg/clustering/__init__.py
ml-wg/clustering/hierarchical.py
ml-wg/clustering/modularity_based.py
ml-wg/clustering/spectral.py
ml-wg/embedding/__init__.py
ml-wg/embedding/deepwalk.py
ml-wg/embedding/line.py
ml-wg/embedding/node2vec.py
ml-wg/gnn/__init__.py
ml-wg/gnn/gae.py
ml-wg/gnn/gat.py
ml-wg/gnn/gcn.py
ml-wg/gnn/generative.py
ml-wg/gnn/grn.py
ml-wg/link_prediction/__init__.py
ml-wg/link_prediction/adamic_adar.py
ml-wg/link_prediction/common_neighbors.py
ml-wg/link_prediction/matrix_factorization.py
ml_wg/__init__.py
ml_wg/utils.py
ml_wg/classification/__init__.py
ml_wg/classification/graph_kernels.py
ml_wg/classification/wl_kernel.py
ml_wg/clustering/__init__.py
ml_wg/clustering/hierarchical.py
ml_wg/clustering/modularity_based.py
ml_wg/clustering/spectral.py
ml_wg/embedding/__init__.py
ml_wg/embedding/deepwalk.py
ml_wg/embedding/line.py
ml_wg/embedding/node2vec.py
ml_wg/gnn/__init__.py
ml_wg/gnn/gae.py
ml_wg/gnn/gat.py
ml_wg/gnn/gcn.py
ml_wg/gnn/generative.py
ml_wg/gnn/grn.py
ml_wg/link_prediction/__init__.py
ml_wg/link_prediction/adamic_adar.py
ml_wg/link_prediction/common_neighbors.py
ml_wg/link_prediction/matrix_factorization.py
machine_learning_with_graph-0.0.3.dist-info/LICENSE
machine_learning_with_graph-0.0.3.dist-info/METADATA
machine_learning_with_graph-0.0.3.dist-info/WHEEL
machine_learning_with_graph-0.0.3.dist-info/top_level.txt
machine_learning_with_graph-0.0.3.dist-info/RECORD
